smallworld_api/__init__.py
smallworld_api/base.py
smallworld_api/common_db.py
smallworld_api/defaults.py
smallworld_api/extras.py
smallworld_api/nomatcherror.py
smallworld_api/search.py
smallworld_api-1.1.1.dist-info/LICENSE
smallworld_api-1.1.1.dist-info/METADATA
smallworld_api-1.1.1.dist-info/WHEEL
smallworld_api-1.1.1.dist-info/top_level.txt
smallworld_api-1.1.1.dist-info/RECORD
