Metadata-Version: 2.1
Name: smallworld-api
Version: 1.1.1
Summary: An (unofficial) Python3 module to query the SmallWorld chemical space search server (https://sw.docking.org/search.html)
Home-page: https://github.com/matteoferla/Python_SmallWorld_API
Author: Matteo Ferla
Author-email: matteo@well.ox.ac.uk
License: MIT
Classifier: Development Status :: 5 - Production/Stable
Classifier: Intended Audience :: Science/Research
Classifier: Topic :: Scientific/Engineering :: Chemistry
Classifier: License :: OSI Approved :: MIT License
Classifier: Programming Language :: Python :: 3.7
Classifier: Programming Language :: Python :: 3.8
Classifier: Programming Language :: Python :: 3.9
Requires-Python: >=3.7
License-File: LICENSE
Requires-Dist: pandas
Requires-Dist: requests
Requires-Dist: ipython
